genaicommit/__init__.py
genaicommit/main.py
genaicommit-0.1.0.dist-info/LICENSE
genaicommit-0.1.0.dist-info/METADATA
genaicommit-0.1.0.dist-info/WHEEL
genaicommit-0.1.0.dist-info/entry_points.txt
genaicommit-0.1.0.dist-info/top_level.txt
genaicommit-0.1.0.dist-info/RECORD
