Metadata-Version: 2.1
Name: genaicommit
Version: 0.1.0
Summary: AI-powered git commit message generator
Home-page: https://github.com/abdul/genaicommit
Author: Abdul Qabiz
Author-email: abdul.qabiz@gmail.com
Classifier: Programming Language :: Python :: 3
Classifier: License :: OSI Approved :: MIT License
Classifier: Operating System :: OS Independent
Requires-Python: >=3.6
License-File: LICENSE
Requires-Dist: inquirer
Requires-Dist: cryptography
Requires-Dist: colorama
